print_position/__init__.py
print_position/print_position.py
print_position-2.0.1.dist-info/LICENSE
print_position-2.0.1.dist-info/METADATA
print_position-2.0.1.dist-info/WHEEL
print_position-2.0.1.dist-info/top_level.txt
print_position-2.0.1.dist-info/RECORD
