Metadata-Version: 2.1
Name: print_position
Version: 2.0.1
Summary: A cool python package to add the timestamp, line number and file name in the print statements.
Home-page: https://github.com/ps428/PrintPosition-pip
Author: Pranav Soni
Author-email: pranav.bhawan@gmail.com
Project-URL: Bug Tracker, https://github.com/ps428/PrintPosition-pip/issues
Project-URL: repository, https://github.com/ps428/PrintPosition-pip
Classifier: Programming Language :: Python :: 3
Classifier: License :: OSI Approved :: MIT License
Classifier: Operating System :: OS Independent
Requires-Python: >=3.6
License-File: LICENSE
